tmlt_core-0.18.2.dist-info/RECORD
tmlt_core-0.18.2.dist-info/LICENSE
tmlt_core-0.18.2.dist-info/LICENSE.docs
tmlt_core-0.18.2.dist-info/WHEEL
tmlt_core-0.18.2.dist-info/NOTICE
tmlt_core-0.18.2.dist-info/METADATA
tmlt_core.dylibs/libflint-17.dylib
tmlt_core.dylibs/libgmp.10.dylib
tmlt_core.dylibs/libmpfr.6.dylib
tmlt/core/metrics.py
tmlt/core/__init__.py
tmlt/core/measures.py
tmlt/core/py.typed
tmlt/core/exceptions.py
tmlt/core/domains/spark_domains.py
tmlt/core/domains/numpy_domains.py
tmlt/core/domains/__init__.py
tmlt/core/domains/collections.py
tmlt/core/domains/pandas_domains.py
tmlt/core/domains/base.py
tmlt/core/transformations/__init__.py
tmlt/core/transformations/chaining.py
tmlt/core/transformations/converters.py
tmlt/core/transformations/dictionary.py
tmlt/core/transformations/identity.py
tmlt/core/transformations/base.py
tmlt/core/transformations/spark_transformations/partition.py
tmlt/core/transformations/spark_transformations/id.py
tmlt/core/transformations/spark_transformations/rename.py
tmlt/core/transformations/spark_transformations/persist.py
tmlt/core/transformations/spark_transformations/__init__.py
tmlt/core/transformations/spark_transformations/join.py
tmlt/core/transformations/spark_transformations/add_remove_keys.py
tmlt/core/transformations/spark_transformations/truncation.py
tmlt/core/transformations/spark_transformations/map.py
tmlt/core/transformations/spark_transformations/nan.py
tmlt/core/transformations/spark_transformations/filter.py
tmlt/core/transformations/spark_transformations/select.py
tmlt/core/transformations/spark_transformations/agg.py
tmlt/core/transformations/spark_transformations/groupby.py
tmlt/core/ext/__init__.py
tmlt/core/ext/lib/libmpfr.la
tmlt/core/ext/lib/GMPVER
tmlt/core/ext/lib/AUDITWHEEL_PLAT
tmlt/core/ext/lib/__init__.py
tmlt/core/ext/lib/FLINTVER
tmlt/core/ext/lib/ARBVER
tmlt/core/ext/lib/libflint-17.dylib
tmlt/core/ext/lib/libgmp.la
tmlt/core/ext/lib/ARCH
tmlt/core/ext/lib/MPFRVER
tmlt/core/ext/lib/libgmp.10.dylib
tmlt/core/ext/lib/libmpfr.6.dylib
tmlt/core/ext/lib/libarb-2.14.0.dylib
tmlt/core/utils/configuration.py
tmlt/core/utils/grouped_dataframe.py
