Metadata-Version: 2.3
Name: tmlt.core
Version: 0.18.2
Summary: Tumult's differential privacy primitives
License: Apache-2.0
Requires-Python: >=3.9.0,<3.13
Classifier: Development Status :: 4 - Beta
Classifier: Intended Audience :: Developers
Classifier: Intended Audience :: Science/Research
Classifier: License :: OSI Approved :: Apache Software License
Classifier: Natural Language :: English
Classifier: Programming Language :: Python :: 3
Classifier: Programming Language :: Python :: 3.9
Classifier: Programming Language :: Python :: 3.10
Classifier: Programming Language :: Python :: 3.11
Classifier: Programming Language :: Python :: 3.12
Classifier: Topic :: Scientific/Engineering
Classifier: Topic :: Security
Classifier: Topic :: Software Development :: Libraries
Classifier: Topic :: Software Development :: Libraries :: Python Modules
Requires-Dist: numpy (>=1.23.2,<2.0.0) ; python_version >= "3.9" and python_version < "3.12"
Requires-Dist: numpy (>=1.26.0,<2.0.0) ; python_version >= "3.12"
Requires-Dist: pandas (>=1.4.0,<2.0.0) ; python_version >= "3.9" and python_version < "3.11"
Requires-Dist: pandas (>=1.5.0,<2.0.0) ; python_version == "3.11"
Requires-Dist: pandas (>=2.2.0,<3.0.0) ; python_version >= "3.12"
Requires-Dist: parameterized (>=0.7.4,<0.8.0)
Requires-Dist: pyarrow (>=18.0.0,<19.0.0)
Requires-Dist: pyspark[sql] (>=3.3.1,<3.6.0) ; python_version >= "3.9" and python_version < "3.11"
Requires-Dist: pyspark[sql] (>=3.4.0,<3.6.0) ; python_version == "3.11"
Requires-Dist: pyspark[sql] (>=3.5.0,<3.6.0) ; python_version >= "3.12"
Requires-Dist: pytest (>=7.3.1,<8.0.0)
Requires-Dist: randomgen (>=1.20.0,<=1.26.0) ; python_version == "3.9"
Requires-Dist: randomgen (>=1.23.0,<=1.26.0) ; python_version == "3.10"
Requires-Dist: randomgen (>=1.26.0,<2.0.0) ; python_version >= "3.11"
Requires-Dist: scipy (>=1.11.2,<2.0.0) ; python_version >= "3.12"
Requires-Dist: scipy (>=1.6.0,<2.0.0) ; python_version == "3.9"
Requires-Dist: scipy (>=1.8.0,<2.0.0) ; python_version == "3.10"
Requires-Dist: scipy (>=1.9.2,<2.0.0) ; python_version == "3.11"
Requires-Dist: setuptools (>=70.0.0,<71.0.0)
Requires-Dist: sympy (>=1.8,<1.13)
Requires-Dist: typeguard (>=4.0.0,<5.0.0)
Project-URL: Documentation, https://docs.tmlt.dev/core/latest
Project-URL: Repository, https://gitlab.com/tumult-labs/core
